baselinr/__init__.py
baselinr/cli.py
baselinr/cli_output.py
baselinr/client.py
baselinr/planner.py
baselinr/anomaly/__init__.py
baselinr/anomaly/anomaly_types.py
baselinr/anomaly/detection_methods.py
baselinr/anomaly/detector.py
baselinr/chat/__init__.py
baselinr/chat/agent.py
baselinr/chat/cli.py
baselinr/chat/context.py
baselinr/chat/history.py
baselinr/chat/renderer.py
baselinr/chat/session.py
baselinr/chat/tools.py
baselinr/config/__init__.py
baselinr/config/loader.py
baselinr/config/merger.py
baselinr/config/schema.py
baselinr/connectors/__init__.py
baselinr/connectors/base.py
baselinr/connectors/bigquery.py
baselinr/connectors/factory.py
baselinr/connectors/mysql.py
baselinr/connectors/postgres.py
baselinr/connectors/redshift.py
baselinr/connectors/snowflake.py
baselinr/connectors/sqlite.py
baselinr/contracts/__init__.py
baselinr/contracts/adapter.py
baselinr/contracts/loader.py
baselinr/contracts/odcs_schema.py
baselinr/contracts/validator.py
baselinr/contracts/tests/__init__.py
baselinr/contracts/tests/test_odcs.py
baselinr/drift/__init__.py
baselinr/drift/baseline_selector.py
baselinr/drift/detector.py
baselinr/drift/statistical_tests.py
baselinr/drift/strategies.py
baselinr/drift/type_normalizer.py
baselinr/drift/type_thresholds.py
baselinr/events/__init__.py
baselinr/events/builtin_hooks.py
baselinr/events/event_bus.py
baselinr/events/events.py
baselinr/events/hooks.py
baselinr/incremental/__init__.py
baselinr/incremental/change_detection.py
baselinr/incremental/planner.py
baselinr/incremental/state.py
baselinr/integrations/__init__.py
baselinr/integrations/airflow/__init__.py
baselinr/integrations/airflow/hooks.py
baselinr/integrations/airflow/operators.py
baselinr/integrations/airflow/sensors.py
baselinr/integrations/dagster/__init__.py
baselinr/integrations/dagster/assets.py
baselinr/integrations/dagster/events.py
baselinr/integrations/dagster/sensors.py
baselinr/integrations/dbt/__init__.py
baselinr/integrations/dbt/manifest_parser.py
baselinr-0.9.0.dist-info/licenses/LICENSE
baselinr-0.9.0.dist-info/METADATA
baselinr-0.9.0.dist-info/WHEEL
baselinr-0.9.0.dist-info/entry_points.txt
baselinr-0.9.0.dist-info/top_level.txt
baselinr-0.9.0.dist-info/RECORD
