Metadata-Version: 2.4
Name: baselinr
Version: 0.9.0
Summary: Modern data profiling and drift detection framework
Home-page: https://github.com/baselinrhq/baselinr
Author: Baselinr Contributors
Author-email: Baselinr Contributors <hello@baselinr.io>
License: Apache-2.0
Project-URL: Homepage, https://baselinr.io
Project-URL: Website, https://baselinr.io
Project-URL: Documentation, https://github.com/baselinrhq/baselinr/tree/main/docs
Project-URL: Repository, https://github.com/baselinrhq/baselinr
Project-URL: Issues, https://github.com/baselinrhq/baselinr/issues
Keywords: data-profiling,data-quality,drift-detection,data-observability,data-warehouse,snowflake,postgresql,sql,dagster
Classifier: Development Status :: 3 - Alpha
Classifier: Intended Audience :: Developers
Classifier: Topic :: Software Development :: Libraries :: Python Modules
Classifier: Topic :: Database
Classifier: Programming Language :: Python :: 3
Classifier: Programming Language :: Python :: 3.10
Classifier: Programming Language :: Python :: 3.11
Classifier: Programming Language :: Python :: 3.12
Classifier: Programming Language :: Python :: 3.13
Classifier: Programming Language :: Python :: 3.14
Requires-Python: >=3.10
License-File: LICENSE
Requires-Dist: pydantic>=2.0.0
Requires-Dist: pyyaml>=6.0.0
Requires-Dist: sqlalchemy>=2.0.0
Requires-Dist: psycopg2-binary>=2.9.0
Requires-Dist: prometheus_client>=0.19.0
Requires-Dist: rich>=13.0.0
Requires-Dist: openai>=1.0.0
Requires-Dist: anthropic>=0.18.0
Requires-Dist: httpx>=0.24.0
Requires-Dist: tenacity>=8.0.0
Requires-Dist: sqlglot>=23.0.0
Requires-Dist: colorama>=0.4.6
Requires-Dist: networkx>=3.1
Provides-Extra: snowflake
Requires-Dist: snowflake-sqlalchemy>=1.5.0; extra == "snowflake"
Requires-Dist: snowflake-connector-python>=3.0.0; extra == "snowflake"
Provides-Extra: dagster
Requires-Dist: dagster>=1.5.0; extra == "dagster"
Requires-Dist: dagster-webserver>=1.5.0; extra == "dagster"
Requires-Dist: dagster-postgres>=0.21.0; extra == "dagster"
Provides-Extra: dbt
Requires-Dist: dbt-core>=1.5.0; extra == "dbt"
Requires-Dist: dbt-postgres>=1.5.0; extra == "dbt"
Provides-Extra: airflow
Requires-Dist: apache-airflow<3.0.0,>=2.0.0; extra == "airflow"
Provides-Extra: dev
Requires-Dist: pytest>=7.0.0; extra == "dev"
Requires-Dist: pytest-cov>=4.0.0; extra == "dev"
Requires-Dist: pytest-asyncio>=0.21.0; extra == "dev"
Requires-Dist: black>=23.0.0; extra == "dev"
Requires-Dist: flake8>=6.0.0; extra == "dev"
Requires-Dist: mypy>=1.0.0; extra == "dev"
Requires-Dist: isort>=5.12.0; extra == "dev"
Provides-Extra: all
Requires-Dist: snowflake-sqlalchemy>=1.5.0; extra == "all"
Requires-Dist: snowflake-connector-python>=3.0.0; extra == "all"
Requires-Dist: dagster>=1.5.0; extra == "all"
Requires-Dist: dagster-webserver>=1.5.0; extra == "all"
Requires-Dist: dagster-postgres>=0.21.0; extra == "all"
Requires-Dist: dbt-core>=1.5.0; extra == "all"
Requires-Dist: dbt-postgres>=1.5.0; extra == "all"
Requires-Dist: apache-airflow<3.0.0,>=2.0.0; extra == "all"
Dynamic: author
Dynamic: home-page
Dynamic: license-file
Dynamic: requires-python
